gnome_extension_publisher/__init__.py
gnome_extension_publisher/cli.py
gnome_extension_publisher/utils.py
gnome_extension_publisher-0.4.11.dist-info/LICENSE
gnome_extension_publisher-0.4.11.dist-info/METADATA
gnome_extension_publisher-0.4.11.dist-info/WHEEL
gnome_extension_publisher-0.4.11.dist-info/entry_points.txt
gnome_extension_publisher-0.4.11.dist-info/RECORD
