Metadata-Version: 2.3
Name: gnome-extension-publisher
Version: 0.4.11
Summary: 
Author: David O Neill
Author-email: dmz.oneill@gmail.com
Requires-Python: >=3.8,<4.0
Classifier: Programming Language :: Python :: 3
Classifier: Programming Language :: Python :: 3.8
Classifier: Programming Language :: Python :: 3.9
Classifier: Programming Language :: Python :: 3.10
Classifier: Programming Language :: Python :: 3.11
Classifier: Programming Language :: Python :: 3.12
Classifier: Programming Language :: Python :: 3.13
Requires-Dist: requests
Requires-Dist: typer
Project-URL: Repository, https://github.com/dmzoneill/gnome-extension-publisher
